mini_transformer/__init__.py
mini_transformer/layer.py
mini_transformer-0.0.1.dist-info/METADATA
mini_transformer-0.0.1.dist-info/WHEEL
mini_transformer-0.0.1.dist-info/licenses/LICENSE
mini_transformer-0.0.1.dist-info/RECORD
